evmrpc/__init__.py
evmrpc/evmrpc.py
evmrpc/rpc.py
evmrpc/utils.py
evmrpc-0.2.1.dist-info/LICENSE
evmrpc-0.2.1.dist-info/WHEEL
evmrpc-0.2.1.dist-info/METADATA
evmrpc-0.2.1.dist-info/RECORD
